{
  "default": "normal",
  "sprite": "opel-0",
  "animation": {
    "name": "opel",
    "duration": 2000000000,
    "cycled": true,
    "blink": 200000000,
    "length": 6
  },
  "items": {
    "appear": {
      "sprite": "opel-0",
      "animation": {
        "name": "opel",
        "duration": 2000000000,
        "cycled": true,
        "blink": 200000000,
        "length": 6
      }
    },
    "normal": {
      "sprite": "opel-0",
      "animation": {
        "name": "opel",
        "duration": 2000000000,
        "cycled": true,
        "length": 6
      }
    }
  }
}